pytradecli/__init__.py
pytradecli/api.py
pytradecli/api_config.py
pytradecli/client.py
pytradecli/utils.py
pytradecli-0.0.4.dist-info/LICENSE
pytradecli-0.0.4.dist-info/METADATA
pytradecli-0.0.4.dist-info/WHEEL
pytradecli-0.0.4.dist-info/top_level.txt
pytradecli-0.0.4.dist-info/RECORD
