Metadata-Version: 2.1
Name: pytradecli
Version: 0.0.4
Summary: pytrade API client
Home-page: UNKNOWN
Author: driller
License: UNKNOWN
Platform: UNKNOWN
Classifier: Programming Language :: Python :: 3.6
Classifier: Programming Language :: Python :: 3.7
Requires-Python: >=3.6, !=3.0.*, !=3.1.*, !=3.2.*, !=3.3.*, !=3.4.*, !=3.5.*
Requires-Dist: pandas
Requires-Dist: requests
